[
  {
    "id": "1",
    "title": "Λύκος καὶ ἀρήν",
    "source": "Aesop's Original Collection",
    "body": "Λύκος θεασάμενος ἄρνα ἀπό τινος ποταμοῦ πίνοντα, τοῦτον ἐβουλήθη μετά τινος εὐλόγου αἰτίας καταθοινήσασθαι. Διόπερ στὰς ἀνωτέρω ᾐτιᾶτο αὐτὸν ὡς θολοῦντα τὸ ὕδωρ καὶ πιεῖν αὐτὸν μὴ ἐῶντα. Τοῦ δὲ λέγοντος ὡς ἄκροις τοῖς χείλεσι πίνει καὶ ἄλλως οὐ δυνατὸν κατωτέρω ἑστῶτα ἐπάνω ταράσσειν τὸ ὕδωρ, ὁ λύκος ἀποτυχὼν\nταύτης τῆς αἰτίας ἔφη· \"Ἀλλὰ πέρυσι τὸν πατέρα μου ἐλοιδόρησας.\" Εἰπόντος δὲ ἐκείνου μηδὲ τότε γεγενῆσθαι, ὁ λύκος ἔφη πρὸς αὐτόν· \"Ἐὰν σὺ ἀπολογιῶν εὐπορῇς, ἐγώ σε οὐχ ἧττον κατέδομαι.”",
    "moral": {
      "type": "explicit",
      "text": "Ὁ λόγος δηλοῖ ὅτι οἷα ἡ πρόθεσίς ἐστιν ἀδικεῖν, παρ’ αὐτοῖς οὐδὲ δικαία ἀπολογία ἰσχύει."
    }
  }
]