{
  "method": "kmeans",
  "n_clusters": 5,
  "feature_type": "tfidf",
  "feature_count": 200,
  "fable_count": 27,
  "quality": {
    "silhouette_score": 0.21745706370110002,
    "calinski_harabasz_score": 5.593003734453558
  },
  "clusters": {
    "cluster_0": {
      "size": 6,
      "fable_ids": [
        "unknown",
        "unknown",
        "unknown",
        "unknown",
        "unknown",
        "unknown"
      ],
      "languages": {
        "en": 6
      },
      "top_features": [
        {
          "name": "the",
          "weight": 0.36642068150847923
        },
        {
          "name": "to",
          "weight": 0.21645762680457295
        },
        {
          "name": "fox",
          "weight": 0.200576007611149
        },
        {
          "name": "you",
          "weight": 0.17709098500365675
        },
        {
          "name": "and",
          "weight": 0.164566426996293
        },
        {
          "name": "mouse",
          "weight": 0.15694511446760395
        },
        {
          "name": "wolf",
          "weight": 0.14598322055149124
        },
        {
          "name": "his",
          "weight": 0.12426858111204452
        },
        {
          "name": "that",
          "weight": 0.1181350929503819
        },
        {
          "name": "of",
          "weight": 0.11805216318450222
        }
      ]
    },
    "cluster_1": {
      "size": 7,
      "fable_ids": [
        "unknown",
        "unknown",
        "unknown",
        "unknown",
        "unknown",
        "unknown",
        "unknown"
      ],
      "languages": {
        "es": 7
      },
      "top_features": [
        {
          "name": "que",
          "weight": 0.31040297741301603
        },
        {
          "name": "de",
          "weight": 0.3071902837368747
        },
        {
          "name": "el",
          "weight": 0.26995751979485677
        },
        {
          "name": "la",
          "weight": 0.22303687476874665
        },
        {
          "name": "un",
          "weight": 0.21934988216647927
        },
        {
          "name": "se",
          "weight": 0.21375385623632112
        },
        {
          "name": "una",
          "weight": 0.16874619030446164
        },
        {
          "name": "con",
          "weight": 0.1623934963478855
        },
        {
          "name": "le",
          "weight": 0.13763944494419636
        },
        {
          "name": "dijo",
          "weight": 0.13327139861678222
        }
      ]
    },
    "cluster_2": {
      "size": 5,
      "fable_ids": [
        "unknown",
        "unknown",
        "unknown",
        "unknown",
        "unknown"
      ],
      "languages": {
        "de": 5
      },
      "top_features": [
        {
          "name": "und",
          "weight": 0.39653277638891077
        },
        {
          "name": "der",
          "weight": 0.2488224020010727
        },
        {
          "name": "die",
          "weight": 0.24221269929938966
        },
        {
          "name": "du",
          "weight": 0.20794612031415252
        },
        {
          "name": "sie",
          "weight": 0.18631986923940444
        },
        {
          "name": "sich",
          "weight": 0.16211652683713926
        },
        {
          "name": "mit",
          "weight": 0.14443831072447322
        },
        {
          "name": "ein",
          "weight": 0.13653465213144728
        },
        {
          "name": "zu",
          "weight": 0.13305853584545826
        },
        {
          "name": "daß",
          "weight": 0.12592035870967502
        }
      ]
    },
    "cluster_3": {
      "size": 7,
      "fable_ids": [
        "unknown",
        "unknown",
        "unknown",
        "unknown",
        "unknown",
        "unknown",
        "unknown"
      ],
      "languages": {
        "nl": 7
      },
      "top_features": [
        {
          "name": "en",
          "weight": 0.24183638827668255
        },
        {
          "name": "de",
          "weight": 0.2231493670752426
        },
        {
          "name": "een",
          "weight": 0.21220577766306056
        },
        {
          "name": "hij",
          "weight": 0.19852448983924068
        },
        {
          "name": "het",
          "weight": 0.18484743691308755
        },
        {
          "name": "van",
          "weight": 0.1477788806629424
        },
        {
          "name": "ze",
          "weight": 0.14727271932599548
        },
        {
          "name": "leeuw",
          "weight": 0.13614108957548163
        },
        {
          "name": "dat",
          "weight": 0.12881213211010195
        },
        {
          "name": "maar",
          "weight": 0.12520532030446543
        }
      ]
    },
    "cluster_4": {
      "size": 2,
      "fable_ids": [
        "unknown",
        "unknown"
      ],
      "languages": {
        "de": 2
      },
      "top_features": [
        {
          "name": "das",
          "weight": 0.4778236352472415
        },
        {
          "name": "mäuschen",
          "weight": 0.27421523679572896
        },
        {
          "name": "ich",
          "weight": 0.2630942418565731
        },
        {
          "name": "und",
          "weight": 0.2599886818094322
        },
        {
          "name": "lämmchen",
          "weight": 0.18220502550493464
        },
        {
          "name": "mir",
          "weight": 0.17833106746913563
        },
        {
          "name": "der",
          "weight": 0.1556812225355163
        },
        {
          "name": "löwen",
          "weight": 0.14619724446305582
        },
        {
          "name": "so",
          "weight": 0.13578228442533608
        },
        {
          "name": "ein",
          "weight": 0.1197181577069671
        }
      ]
    }
  },
  "fable_clusters": {
    "unknown": 1
  }
}