[
  {
    "categories": [],
    "dominant_category": null,
    "fable_id": "1",
    "title": "Das Lamm und Der Wolf",
    "moral_text": "Die Moral ist, tot zu lämmchen."
  },
  {
    "categories": [],
    "dominant_category": null,
    "fable_id": "2",
    "title": "Die Stadt und Die Landmaus",
    "moral_text": "Die Moral ist, freundin zu landmaus."
  },
  {
    "categories": [],
    "dominant_category": null,
    "fable_id": "3",
    "title": "Der Fuchs und die Trauben",
    "moral_text": "Die Moral ist, fuchs zu trauben."
  },
  {
    "categories": [],
    "dominant_category": null,
    "fable_id": "4",
    "title": "Der Wolf und Der Kranich",
    "moral_text": "Die Moral ist, rachen zu belohnung."
  },
  {
    "categories": [],
    "dominant_category": null,
    "fable_id": "5",
    "title": "Der Löwe und das Mäuschen",
    "moral_text": "Die Moral ist, löwen zu mäuschen."
  },
  {
    "categories": [],
    "dominant_category": null,
    "fable_id": "6",
    "title": "Der Löwe und Die Mücke",
    "moral_text": "Die Moral ist, spinne zu mücke."
  },
  {
    "categories": [],
    "dominant_category": null,
    "fable_id": "7",
    "title": "Der Fuchs und der Bock",
    "moral_text": "Die Moral ist, fuchs zu bock."
  }
]